toomoss_py/__init__.py
toomoss_py/api/can_uds.py
toomoss_py/api/dbc_parser.py
toomoss_py/api/elmos_programer.py
toomoss_py/api/ldf_parser.py
toomoss_py/api/lin_uds.py
toomoss_py/api/mlx_programer.py
toomoss_py/api/usb2adc.py
toomoss_py/api/usb2ads1256.py
toomoss_py/api/usb2bmm_lin.py
toomoss_py/api/usb2can.py
toomoss_py/api/usb2canfd.py
toomoss_py/api/usb2dio.py
toomoss_py/api/usb2gpio.py
toomoss_py/api/usb2iic.py
toomoss_py/api/usb2lin.py
toomoss_py/api/usb2lin_ex.py
toomoss_py/api/usb2melibu.py
toomoss_py/api/usb2pwm.py
toomoss_py/api/usb2sent.py
toomoss_py/api/usb2spi.py
toomoss_py/api/usb2uart.py
toomoss_py/api/usb_device.py
toomoss_py/libs/android/libs/arm64-v8a/libUSB2XXX.so
toomoss_py/libs/android/libs/arm64-v8a/libc++_shared.so
toomoss_py/libs/android/libs/arm64-v8a/libjnidispatch.so
toomoss_py/libs/android/libs/arm64-v8a/libusb.so
toomoss_py/libs/android/libs/armeabi-v7a/libUSB2XXX.so
toomoss_py/libs/android/libs/armeabi-v7a/libc++_shared.so
toomoss_py/libs/android/libs/armeabi-v7a/libjnidispatch.so
toomoss_py/libs/android/libs/armeabi-v7a/libusb.so
toomoss_py/libs/android/libs/x86/libUSB2XXX.so
toomoss_py/libs/android/libs/x86/libc++_shared.so
toomoss_py/libs/android/libs/x86/libusb.so
toomoss_py/libs/android/libs/x86_64/libUSB2XXX.so
toomoss_py/libs/android/libs/x86_64/libc++_shared.so
toomoss_py/libs/android/libs/x86_64/libusb.so
toomoss_py/libs/linux/README.md
toomoss_py/libs/linux/aarch64/libUSB2XXX.so
toomoss_py/libs/linux/aarch64/libusb-1.0.so
toomoss_py/libs/linux/arm64/libUSB2XXX.so
toomoss_py/libs/linux/arm64/libusb-1.0.so
toomoss_py/libs/linux/armv7/libUSB2XXX.so
toomoss_py/libs/linux/armv7/libusb-1.0.so
toomoss_py/libs/linux/mips64/libUSB2XXX.so
toomoss_py/libs/linux/mips64/libusb-1.0.so
toomoss_py/libs/linux/x86/libUSB2XXX.so
toomoss_py/libs/linux/x86/libusb-1.0.so
toomoss_py/libs/linux/x86_64/libUSB2XXX.so
toomoss_py/libs/linux/x86_64/libusb-1.0.so
toomoss_py/libs/mac_os/libUSB2XXX.dylib
toomoss_py/libs/mac_os/libusb-1.0.0.dylib
toomoss_py-0.1.2.dist-info/WHEEL
toomoss_py-0.1.2.dist-info/METADATA
toomoss_py-0.1.2.dist-info/RECORD
