Metadata-Version: 2.3
Name: toomoss-py
Version: 0.1.2
Summary: Python Wrapper for Toomoss USB
Requires-Python: >=3.9
Project-URL: homepage, https://github.com/mikisama/toomoss_py
